pfhm/__init__.py
pfhm/profiler.py
pfhm-0.3.dist-info/LICENSE
pfhm-0.3.dist-info/METADATA
pfhm-0.3.dist-info/WHEEL
pfhm-0.3.dist-info/top_level.txt
pfhm-0.3.dist-info/RECORD
