Metadata-Version: 2.1
Name: pfhm
Version: 0.3
Home-page: https://github.com/OllieBoyne/pfhm
License: LICENSE
License-File: LICENSE
Requires-Dist: numpy
